mdv/__init__.py
mdv/ansi_tables.json
mdv/markdownviewer.py
mdv/tabulate.py
mdv/tests/__init__.py
mdv/tests/test_files.py
mdv/tests/test_inline.py
mdv3-2.0.2.dist-info/LICENSE
mdv3-2.0.2.dist-info/LICENSE.txt
mdv3-2.0.2.dist-info/METADATA
mdv3-2.0.2.dist-info/WHEEL
mdv3-2.0.2.dist-info/entry_points.txt
mdv3-2.0.2.dist-info/top_level.txt
mdv3-2.0.2.dist-info/RECORD
