Metadata-Version: 2.1
Name: mdv3
Version: 2.0.2
Summary: Terminal Markdown Viewer
Home-page: http://github.com/WillNye/terminal_markdown_viewer
Author: Will Beasley
Author-email: willbeas88@gmail.com
License: UNKNOWN
Download-URL: http://github.com/WillNye/terminal_markdown_viewer/tarball/
Keywords: markdown,markup,terminal,hilighting,syntax,source code
Platform: UNKNOWN
Classifier: Programming Language :: Python
Classifier: Natural Language :: English
Classifier: Operating System :: POSIX
Classifier: Topic :: Text Processing :: Markup
Classifier: License :: OSI Approved :: BSD License
Classifier: Programming Language :: Python :: 3.7
Classifier: Programming Language :: Python :: 3.8
Classifier: Programming Language :: Python :: 3.9
Requires-Python: >=3.7
Requires-Dist: markdown
Requires-Dist: pygments
Requires-Dist: six
Requires-Dist: tabulate
Provides-Extra: yaml
Requires-Dist: pyyaml ; extra == 'yaml'
